<?xml version="1.0" encoding="UTF-8"?>

<FLOW VERSION="3.0" CLEANUP="true">
  <COMMENT></COMMENT>

  <!-- nodes -->

<SEQUENCE TIMEOUT="" EXIT-ON="FAILURE">
  <COMMENT>--Map Process Data--</COMMENT>

  <!-- nodes -->

<INVOKE TIMEOUT="" SERVICE="pub.monitor.process.instanceSteps:getStepActivityLogs" VALIDATE-IN="$none" VALIDATE-OUT="$none">
  <COMMENT>--Get Step Activity Logs --</COMMENT>

  <!-- nodes -->

<MAP MODE="INPUT">
  <MAPTARGET>

<Values version="2.0">
  <record name="xml" javaclass="com.wm.util.Values">
    <value name="node_type">record</value>
    <value name="node_subtype">unknown</value>
    <value name="is_public">false</value>
    <value name="field_name">getStepActivityLogsInput</value>
    <value name="field_type">record</value>
    <value name="field_dim">0</value>
    <value name="nillable">true</value>
    <value name="form_qualified">false</value>
    <value name="is_global">false</value>
    <array name="rec_fields" type="record" depth="1">
      <record javaclass="com.wm.util.Values">
        <value name="node_type">field</value>
        <value name="node_subtype">unknown</value>
        <value name="is_public">false</value>
        <value name="field_name">instanceID</value>
        <value name="field_type">string</value>
        <value name="field_dim">0</value>
        <value name="nillable">true</value>
        <value name="form_qualified">false</value>
        <value name="is_global">false</value>
      </record>
      <record javaclass="com.wm.util.Values">
        <value name="node_type">field</value>
        <value name="node_subtype">unknown</value>
        <value name="is_public">false</value>
        <value name="field_name">instanceIteration</value>
        <value name="field_type">string</value>
        <value name="field_dim">0</value>
        <value name="field_opt">true</value>
        <value name="nillable">true</value>
        <value name="form_qualified">false</value>
        <value name="is_global">false</value>
      </record>
      <record javaclass="com.wm.util.Values">
        <value name="node_type">field</value>
        <value name="node_subtype">unknown</value>
        <value name="is_public">false</value>
        <value name="field_name">stepID</value>
        <value name="field_type">string</value>
        <value name="field_dim">0</value>
        <value name="field_opt">true</value>
        <value name="nillable">true</value>
        <value name="form_qualified">false</value>
        <value name="is_global">false</value>
      </record>
      <record javaclass="com.wm.util.Values">
        <value name="node_type">field</value>
        <value name="node_subtype">unknown</value>
        <value name="is_public">false</value>
        <value name="field_name">stepIteration</value>
        <value name="field_type">string</value>
        <value name="field_dim">0</value>
        <value name="field_opt">true</value>
        <value name="nillable">true</value>
        <value name="form_qualified">false</value>
        <value name="is_global">false</value>
      </record>
    </array>
    <value name="modifiable">true</value>
  </record>
</Values>
</MAPTARGET>
  <MAPSOURCE>

<Values version="2.0">
  <record name="xml" javaclass="com.wm.util.Values">
    <value name="node_type">record</value>
    <value name="node_subtype">unknown</value>
    <value name="is_public">false</value>
    <value name="field_type">record</value>
    <value name="field_dim">0</value>
    <value name="nillable">true</value>
    <value name="form_qualified">false</value>
    <value name="is_global">false</value>
    <array name="rec_fields" type="record" depth="1">
    </array>
    <value name="modifiable">true</value>
  </record>
</Values>
</MAPSOURCE>

  <!-- nodes -->

<MAPSET NAME="Setter" OVERWRITE="true" VARIABLES="true" GLOBALVARIABLES="false" FIELD="/instanceID;1;0">
  <DATA ENCODING="XMLValues" I18N="true">

<Values version="2.0">
  <value name="xml">%instances/INSTANCEID%</value>
  <record name="type" javaclass="com.wm.util.Values">
    <value name="node_type">field</value>
    <value name="node_subtype">unknown</value>
    <value name="is_public">false</value>
    <value name="field_name">instanceID</value>
    <value name="field_type">string</value>
    <value name="field_dim">0</value>
    <value name="nillable">true</value>
    <value name="form_qualified">false</value>
    <value name="is_global">false</value>
  </record>
</Values>
</DATA>
</MAPSET>
</MAP>
</INVOKE>

<MAP TIMEOUT="" MODE="STANDALONE">
  <COMMENT>--get Stage Number--</COMMENT>
  <MAPTARGET>

<Values version="2.0">
  <record name="xml" javaclass="com.wm.util.Values">
    <value name="node_type">record</value>
    <value name="node_subtype">unknown</value>
    <value name="is_public">false</value>
    <value name="field_type">record</value>
    <value name="field_dim">0</value>
    <value name="nillable">true</value>
    <value name="form_qualified">false</value>
    <value name="is_global">false</value>
    <array name="rec_fields" type="record" depth="1">
      <record javaclass="com.wm.util.Values">
        <value name="node_type">unknown</value>
        <value name="node_subtype">unknown</value>
        <value name="is_public">false</value>
        <value name="field_name">instanceID</value>
        <value name="field_type">string</value>
        <value name="field_dim">0</value>
        <value name="nillable">true</value>
        <value name="form_qualified">false</value>
        <value name="is_global">false</value>
      </record>
      <record javaclass="com.wm.util.Values">
        <value name="node_type">unknown</value>
        <value name="node_subtype">unknown</value>
        <value name="is_public">false</value>
        <value name="field_name">stageNo</value>
        <value name="field_type">string</value>
        <value name="field_dim">0</value>
        <value name="nillable">true</value>
        <value name="form_qualified">false</value>
        <value name="is_global">false</value>
      </record>
      <record javaclass="com.wm.util.Values">
        <value name="node_type">record</value>
        <value name="node_subtype">unknown</value>
        <value name="node_comment"></value>
        <record name="node_hints" javaclass="com.wm.util.Values">
          <value name="field_largerEditor">false</value>
          <value name="field_password">false</value>
        </record>
        <value name="is_public">false</value>
        <value name="field_name">instances</value>
        <value name="field_type">record</value>
        <value name="field_dim">0</value>
        <value name="wrapper_type">IData</value>
        <value name="nillable">true</value>
        <value name="form_qualified">false</value>
        <value name="is_global">false</value>
        <array name="rec_fields" type="record" depth="1">
        </array>
        <value name="rec_closed">true</value>
        <value name="modifiable">true</value>
      </record>
    </array>
    <value name="modifiable">true</value>
  </record>
</Values>
</MAPTARGET>
  <MAPSOURCE>

<Values version="2.0">
  <record name="xml" javaclass="com.wm.util.Values">
    <value name="node_type">record</value>
    <value name="node_subtype">unknown</value>
    <value name="is_public">false</value>
    <value name="field_type">record</value>
    <value name="field_dim">0</value>
    <value name="nillable">true</value>
    <value name="form_qualified">false</value>
    <value name="is_global">false</value>
    <array name="rec_fields" type="record" depth="1">
      <record javaclass="com.wm.util.Values">
        <value name="node_type">unknown</value>
        <value name="node_subtype">unknown</value>
        <value name="is_public">false</value>
        <value name="field_name">instanceID</value>
        <value name="field_type">string</value>
        <value name="field_dim">0</value>
        <value name="nillable">true</value>
        <value name="form_qualified">false</value>
        <value name="is_global">false</value>
      </record>
      <record javaclass="com.wm.util.Values">
        <value name="node_type">record</value>
        <value name="node_subtype">unknown</value>
        <value name="node_comment"></value>
        <record name="node_hints" javaclass="com.wm.util.Values">
          <value name="field_largerEditor">false</value>
          <value name="field_password">false</value>
        </record>
        <value name="is_public">false</value>
        <value name="field_name">instances</value>
        <value name="field_type">record</value>
        <value name="field_dim">0</value>
        <value name="wrapper_type">IData</value>
        <value name="nillable">true</value>
        <value name="form_qualified">false</value>
        <value name="is_global">false</value>
        <array name="rec_fields" type="record" depth="1">
        </array>
        <value name="rec_closed">true</value>
        <value name="modifiable">true</value>
      </record>
      <record javaclass="com.wm.util.Values">
        <value name="node_type">record</value>
        <value name="node_subtype">unknown</value>
        <value name="is_public">false</value>
        <value name="field_name">activityLogData</value>
        <value name="field_type">record</value>
        <value name="field_dim">1</value>
        <value name="nillable">true</value>
        <value name="form_qualified">false</value>
        <value name="is_global">false</value>
        <value name="is_soap_array_encoding_used">false</value>
        <array name="rec_fields" type="record" depth="1">
        </array>
        <value name="modifiable">true</value>
      </record>
      <record javaclass="com.wm.util.Values">
        <value name="node_type">field</value>
        <value name="node_subtype">unknown</value>
        <value name="is_public">false</value>
        <value name="field_name">message</value>
        <value name="field_type">string</value>
        <value name="field_dim">0</value>
        <value name="field_opt">true</value>
        <value name="nillable">true</value>
        <value name="form_qualified">false</value>
        <value name="is_global">false</value>
      </record>
    </array>
    <value name="modifiable">true</value>
  </record>
</Values>
</MAPSOURCE>

  <!-- nodes -->

<MAPINVOKE SERVICE="pub.string:replace" VALIDATE-IN="$none" VALIDATE-OUT="$none" INVOKE-ORDER="0">

  <!-- nodes -->

<MAP MODE="INVOKEINPUT">
  <MAPTARGET>

<Values version="2.0">
  <record name="xml" javaclass="com.wm.util.Values">
    <value name="node_type">record</value>
    <value name="node_subtype">unknown</value>
    <value name="is_public">false</value>
    <value name="field_name">replaceInput</value>
    <value name="field_type">record</value>
    <value name="field_dim">0</value>
    <value name="nillable">true</value>
    <value name="form_qualified">false</value>
    <value name="is_global">false</value>
    <array name="rec_fields" type="record" depth="1">
      <record javaclass="com.wm.util.Values">
        <value name="node_type">field</value>
        <value name="node_subtype">unknown</value>
        <value name="is_public">false</value>
        <value name="field_name">inString</value>
        <value name="field_type">string</value>
        <value name="field_dim">0</value>
        <value name="nillable">true</value>
        <value name="form_qualified">false</value>
        <value name="is_global">false</value>
      </record>
      <record javaclass="com.wm.util.Values">
        <value name="node_type">field</value>
        <value name="node_subtype">unknown</value>
        <value name="is_public">false</value>
        <value name="field_name">searchString</value>
        <value name="field_type">string</value>
        <value name="field_dim">0</value>
        <value name="nillable">true</value>
        <value name="form_qualified">false</value>
        <value name="is_global">false</value>
      </record>
      <record javaclass="com.wm.util.Values">
        <value name="node_type">field</value>
        <value name="node_subtype">unknown</value>
        <value name="is_public">false</value>
        <value name="field_name">replaceString</value>
        <value name="field_type">string</value>
        <value name="field_dim">0</value>
        <value name="nillable">true</value>
        <value name="form_qualified">false</value>
        <value name="is_global">false</value>
      </record>
      <record javaclass="com.wm.util.Values">
        <value name="node_type">field</value>
        <value name="node_subtype">unknown</value>
        <value name="is_public">false</value>
        <value name="field_name">useRegex</value>
        <value name="field_type">string</value>
        <value name="field_dim">0</value>
        <value name="field_opt">true</value>
        <array name="field_options" type="value" depth="1">
          <value>false</value>
          <value>true</value>
        </array>
        <value name="nillable">true</value>
        <value name="form_qualified">false</value>
        <value name="is_global">false</value>
      </record>
    </array>
    <value name="modifiable">true</value>
  </record>
</Values>
</MAPTARGET>
  <MAPSOURCE>

<Values version="2.0">
  <record name="xml" javaclass="com.wm.util.Values">
    <value name="node_type">record</value>
    <value name="node_subtype">unknown</value>
    <value name="is_public">false</value>
    <value name="field_type">record</value>
    <value name="field_dim">0</value>
    <value name="nillable">true</value>
    <value name="form_qualified">false</value>
    <value name="is_global">false</value>
    <array name="rec_fields" type="record" depth="1">
    </array>
    <value name="modifiable">true</value>
  </record>
</Values>
</MAPSOURCE>

  <!-- nodes -->

<MAPSET NAME="Setter" OVERWRITE="true" VARIABLES="false" GLOBALVARIABLES="false" FIELD="/searchString;1;0">
  <DATA ENCODING="XMLValues" I18N="true">

<Values version="2.0">
  <value name="xml">Stage</value>
  <record name="type" javaclass="com.wm.util.Values">
    <value name="node_type">field</value>
    <value name="node_subtype">unknown</value>
    <value name="is_public">false</value>
    <value name="field_name">searchString</value>
    <value name="field_type">string</value>
    <value name="field_dim">0</value>
    <value name="nillable">true</value>
    <value name="form_qualified">false</value>
    <value name="is_global">false</value>
  </record>
</Values>
</DATA>
</MAPSET>

<MAPSET NAME="Setter" OVERWRITE="true" VARIABLES="false" GLOBALVARIABLES="false" FIELD="/replaceString;1;0">
  <DATA ENCODING="XMLValues" I18N="true">

<Values version="2.0">
  <value name="xml"></value>
  <record name="type" javaclass="com.wm.util.Values">
    <value name="node_type">field</value>
    <value name="node_subtype">unknown</value>
    <value name="is_public">false</value>
    <value name="field_name">replaceString</value>
    <value name="field_type">string</value>
    <value name="field_dim">0</value>
    <value name="nillable">true</value>
    <value name="form_qualified">false</value>
    <value name="is_global">false</value>
  </record>
</Values>
</DATA>
</MAPSET>

<MAPSET NAME="Setter" OVERWRITE="true" VARIABLES="true" GLOBALVARIABLES="false" FIELD="/inString;1;0">
  <DATA ENCODING="XMLValues" I18N="true">

<Values version="2.0">
  <value name="xml">%/activityLogData[0]/BRIEFMESSAGE%</value>
  <record name="type" javaclass="com.wm.util.Values">
    <value name="node_type">field</value>
    <value name="node_subtype">unknown</value>
    <value name="is_public">false</value>
    <value name="field_name">inString</value>
    <value name="field_type">string</value>
    <value name="field_dim">0</value>
    <value name="nillable">true</value>
    <value name="form_qualified">false</value>
    <value name="is_global">false</value>
  </record>
</Values>
</DATA>
</MAPSET>
</MAP>

<MAP MODE="INVOKEOUTPUT">
  <MAPTARGET>

<Values version="2.0">
  <record name="xml" javaclass="com.wm.util.Values">
    <value name="node_type">record</value>
    <value name="node_subtype">unknown</value>
    <value name="is_public">false</value>
    <value name="field_type">record</value>
    <value name="field_dim">0</value>
    <value name="nillable">true</value>
    <value name="form_qualified">false</value>
    <value name="is_global">false</value>
    <array name="rec_fields" type="record" depth="1">
      <record javaclass="com.wm.util.Values">
        <value name="node_type">unknown</value>
        <value name="node_subtype">unknown</value>
        <value name="is_public">false</value>
        <value name="field_name">instanceID</value>
        <value name="field_type">string</value>
        <value name="field_dim">0</value>
        <value name="nillable">true</value>
        <value name="form_qualified">false</value>
        <value name="is_global">false</value>
      </record>
      <record javaclass="com.wm.util.Values">
        <value name="node_type">unknown</value>
        <value name="node_subtype">unknown</value>
        <value name="is_public">false</value>
        <value name="field_name">stageNo</value>
        <value name="field_type">string</value>
        <value name="field_dim">0</value>
        <value name="nillable">true</value>
        <value name="form_qualified">false</value>
        <value name="is_global">false</value>
      </record>
      <record javaclass="com.wm.util.Values">
        <value name="node_type">record</value>
        <value name="node_subtype">unknown</value>
        <value name="node_comment"></value>
        <record name="node_hints" javaclass="com.wm.util.Values">
          <value name="field_largerEditor">false</value>
          <value name="field_password">false</value>
        </record>
        <value name="is_public">false</value>
        <value name="field_name">instances</value>
        <value name="field_type">record</value>
        <value name="field_dim">0</value>
        <value name="wrapper_type">IData</value>
        <value name="nillable">true</value>
        <value name="form_qualified">false</value>
        <value name="is_global">false</value>
        <array name="rec_fields" type="record" depth="1">
        </array>
        <value name="rec_closed">true</value>
        <value name="modifiable">true</value>
      </record>
    </array>
    <value name="modifiable">true</value>
  </record>
</Values>
</MAPTARGET>
  <MAPSOURCE>

<Values version="2.0">
  <record name="xml" javaclass="com.wm.util.Values">
    <value name="node_type">record</value>
    <value name="node_subtype">unknown</value>
    <value name="is_public">false</value>
    <value name="field_name">replaceOutput</value>
    <value name="field_type">record</value>
    <value name="field_dim">0</value>
    <value name="nillable">true</value>
    <value name="form_qualified">false</value>
    <value name="is_global">false</value>
    <array name="rec_fields" type="record" depth="1">
      <record javaclass="com.wm.util.Values">
        <value name="node_type">field</value>
        <value name="node_subtype">unknown</value>
        <value name="is_public">false</value>
        <value name="field_name">value</value>
        <value name="field_type">string</value>
        <value name="field_dim">0</value>
        <value name="nillable">true</value>
        <value name="form_qualified">false</value>
        <value name="is_global">false</value>
      </record>
    </array>
    <value name="modifiable">true</value>
  </record>
</Values>
</MAPSOURCE>

  <!-- nodes -->

<MAPCOPY FROM="/value;1;0" TO="/stageNo;1;0">
</MAPCOPY>
</MAP>
</MAPINVOKE>

<MAPDELETE FIELD="/activityLogData;2;1">
</MAPDELETE>

<MAPDELETE FIELD="/message;1;0">
</MAPDELETE>
</MAP>

<BRANCH TIMEOUT="" LABELEXPRESSIONS="true">
  <COMMENT>--Verify Stage Number--</COMMENT>

  <!-- nodes -->

<SEQUENCE NAME="%stageNo% &lt;5.2" TIMEOUT="" EXIT-ON="FAILURE">
  <COMMENT>--Less than Create CIF Stage--</COMMENT>

  <!-- nodes -->

<MAP TIMEOUT="" MODE="STANDALONE">
  <COMMENT>--Map Process Details--</COMMENT>
  <MAPTARGET>

<Values version="2.0">
  <record name="xml" javaclass="com.wm.util.Values">
    <value name="node_type">record</value>
    <value name="node_subtype">unknown</value>
    <value name="is_public">false</value>
    <value name="field_type">record</value>
    <value name="field_dim">0</value>
    <value name="nillable">true</value>
    <value name="form_qualified">false</value>
    <value name="is_global">false</value>
    <array name="rec_fields" type="record" depth="1">
      <record javaclass="com.wm.util.Values">
        <value name="node_type">unknown</value>
        <value name="node_subtype">unknown</value>
        <value name="is_public">false</value>
        <value name="field_name">instanceID</value>
        <value name="field_type">string</value>
        <value name="field_dim">0</value>
        <value name="nillable">true</value>
        <value name="form_qualified">false</value>
        <value name="is_global">false</value>
      </record>
      <record javaclass="com.wm.util.Values">
        <value name="node_type">record</value>
        <value name="node_subtype">unknown</value>
        <value name="is_public">false</value>
        <value name="field_name">processResume</value>
        <value name="field_type">recref</value>
        <value name="field_dim">0</value>
        <value name="nillable">true</value>
        <value name="form_qualified">false</value>
        <value name="is_global">false</value>
        <value name="modifiable">true</value>
        <value name="rec_ref">MdrDbtOnlineOnboarding.documents.process:ResumeProcess</value>
      </record>
      <record javaclass="com.wm.util.Values">
        <value name="node_type">unknown</value>
        <value name="node_subtype">unknown</value>
        <value name="is_public">false</value>
        <value name="field_name">stageNo</value>
        <value name="field_type">string</value>
        <value name="field_dim">0</value>
        <value name="nillable">true</value>
        <value name="form_qualified">false</value>
        <value name="is_global">false</value>
      </record>
      <record javaclass="com.wm.util.Values">
        <value name="node_type">record</value>
        <value name="node_subtype">unknown</value>
        <value name="node_comment"></value>
        <record name="node_hints" javaclass="com.wm.util.Values">
          <value name="field_largerEditor">false</value>
          <value name="field_password">false</value>
        </record>
        <value name="is_public">false</value>
        <value name="field_name">instances</value>
        <value name="field_type">record</value>
        <value name="field_dim">0</value>
        <value name="wrapper_type">IData</value>
        <value name="nillable">true</value>
        <value name="form_qualified">false</value>
        <value name="is_global">false</value>
        <array name="rec_fields" type="record" depth="1">
        </array>
        <value name="rec_closed">true</value>
        <value name="modifiable">true</value>
      </record>
    </array>
    <value name="modifiable">true</value>
  </record>
</Values>
</MAPTARGET>
  <MAPSOURCE>

<Values version="2.0">
  <record name="xml" javaclass="com.wm.util.Values">
    <value name="node_type">record</value>
    <value name="node_subtype">unknown</value>
    <value name="is_public">false</value>
    <value name="field_type">record</value>
    <value name="field_dim">0</value>
    <value name="nillable">true</value>
    <value name="form_qualified">false</value>
    <value name="is_global">false</value>
    <array name="rec_fields" type="record" depth="1">
      <record javaclass="com.wm.util.Values">
        <value name="node_type">unknown</value>
        <value name="node_subtype">unknown</value>
        <value name="is_public">false</value>
        <value name="field_name">instanceID</value>
        <value name="field_type">string</value>
        <value name="field_dim">0</value>
        <value name="nillable">true</value>
        <value name="form_qualified">false</value>
        <value name="is_global">false</value>
      </record>
      <record javaclass="com.wm.util.Values">
        <value name="node_type">unknown</value>
        <value name="node_subtype">unknown</value>
        <value name="is_public">false</value>
        <value name="field_name">stageNo</value>
        <value name="field_type">string</value>
        <value name="field_dim">0</value>
        <value name="nillable">true</value>
        <value name="form_qualified">false</value>
        <value name="is_global">false</value>
      </record>
      <record javaclass="com.wm.util.Values">
        <value name="node_type">record</value>
        <value name="node_subtype">unknown</value>
        <value name="node_comment"></value>
        <record name="node_hints" javaclass="com.wm.util.Values">
          <value name="field_largerEditor">false</value>
          <value name="field_password">false</value>
        </record>
        <value name="is_public">false</value>
        <value name="field_name">instances</value>
        <value name="field_type">record</value>
        <value name="field_dim">0</value>
        <value name="wrapper_type">IData</value>
        <value name="nillable">true</value>
        <value name="form_qualified">false</value>
        <value name="is_global">false</value>
        <array name="rec_fields" type="record" depth="1">
        </array>
        <value name="rec_closed">true</value>
        <value name="modifiable">true</value>
      </record>
    </array>
    <value name="modifiable">true</value>
  </record>
</Values>
</MAPSOURCE>

  <!-- nodes -->

<MAPSET NAME="Setter" OVERWRITE="true" VARIABLES="false" GLOBALVARIABLES="false" FIELD="/processResume;4;0;MdrDbtOnlineOnboarding.documents.process:ResumeProcess/stage;1;0">
  <DATA ENCODING="XMLValues" I18N="true">

<Values version="2.0">
  <value name="xml">Create CIF Account</value>
  <record name="type" javaclass="com.wm.util.Values">
    <value name="node_type">record</value>
    <value name="node_subtype">unknown</value>
    <value name="node_comment"></value>
    <record name="node_hints" javaclass="com.wm.util.Values">
      <value name="field_usereditable">true</value>
      <value name="field_largerEditor">false</value>
      <value name="field_password">false</value>
    </record>
    <value name="is_public">false</value>
    <value name="field_name">stage</value>
    <value name="field_type">string</value>
    <value name="field_dim">0</value>
    <value name="field_opt">true</value>
    <array name="field_options" type="value" depth="1">
    </array>
    <value name="nillable">true</value>
    <value name="form_qualified">false</value>
    <value name="is_global">false</value>
  </record>
</Values>
</DATA>
</MAPSET>

<MAPSET NAME="Setter" OVERWRITE="true" VARIABLES="false" GLOBALVARIABLES="false" FIELD="/processResume;4;0;MdrDbtOnlineOnboarding.documents.process:ResumeProcess/nextStep;1;0">
  <DATA ENCODING="XMLValues" I18N="true">

<Values version="2.0">
  <value name="xml">CREATE_CIF_ACCOUNT</value>
  <record name="type" javaclass="com.wm.util.Values">
    <value name="node_type">record</value>
    <value name="node_subtype">unknown</value>
    <value name="node_comment"></value>
    <record name="node_hints" javaclass="com.wm.util.Values">
      <value name="field_usereditable">true</value>
      <value name="field_largerEditor">false</value>
      <value name="field_password">false</value>
    </record>
    <value name="is_public">false</value>
    <value name="field_name">nextStep</value>
    <value name="field_type">string</value>
    <value name="field_dim">0</value>
    <value name="field_opt">true</value>
    <array name="field_options" type="value" depth="1">
    </array>
    <value name="nillable">true</value>
    <value name="form_qualified">false</value>
    <value name="is_global">false</value>
  </record>
</Values>
</DATA>
</MAPSET>

<MAPCOPY FROM="/instanceID;1;0" TO="/processResume;4;0;MdrDbtOnlineOnboarding.documents.process:ResumeProcess/referenceKey;1;0">
</MAPCOPY>

<MAPSET NAME="Setter" OVERWRITE="true" VARIABLES="false" GLOBALVARIABLES="false" FIELD="/processResume;4;0;MdrDbtOnlineOnboarding.documents.process:ResumeProcess/status;1;0">
  <DATA ENCODING="XMLValues" I18N="true">

<Values version="2.0">
  <value name="xml">Waiting</value>
  <record name="type" javaclass="com.wm.util.Values">
    <value name="node_type">record</value>
    <value name="node_subtype">unknown</value>
    <value name="node_comment"></value>
    <record name="node_hints" javaclass="com.wm.util.Values">
      <value name="field_usereditable">true</value>
      <value name="field_largerEditor">false</value>
      <value name="field_password">false</value>
    </record>
    <value name="is_public">false</value>
    <value name="field_name">status</value>
    <value name="field_type">string</value>
    <value name="field_dim">0</value>
    <value name="field_opt">true</value>
    <array name="field_options" type="value" depth="1">
    </array>
    <value name="nillable">true</value>
    <value name="form_qualified">false</value>
    <value name="is_global">false</value>
  </record>
</Values>
</DATA>
</MAPSET>
</MAP>
</SEQUENCE>

<SEQUENCE NAME="$default" TIMEOUT="" EXIT-ON="FAILURE">
  <COMMENT>--Not Waiting--</COMMENT>

  <!-- nodes -->

<MAP TIMEOUT="" MODE="STANDALONE">
  <COMMENT>--Map Response--</COMMENT>
  <MAPTARGET>

<Values version="2.0">
  <record name="xml" javaclass="com.wm.util.Values">
    <value name="node_type">record</value>
    <value name="node_subtype">unknown</value>
    <value name="is_public">false</value>
    <value name="field_type">record</value>
    <value name="field_dim">0</value>
    <value name="nillable">true</value>
    <value name="form_qualified">false</value>
    <value name="is_global">false</value>
    <array name="rec_fields" type="record" depth="1">
      <record javaclass="com.wm.util.Values">
        <value name="node_type">unknown</value>
        <value name="node_subtype">unknown</value>
        <value name="is_public">false</value>
        <value name="field_name">instanceID</value>
        <value name="field_type">string</value>
        <value name="field_dim">0</value>
        <value name="nillable">true</value>
        <value name="form_qualified">false</value>
        <value name="is_global">false</value>
      </record>
      <record javaclass="com.wm.util.Values">
        <value name="node_type">record</value>
        <value name="node_subtype">unknown</value>
        <value name="is_public">false</value>
        <value name="field_name">processResume</value>
        <value name="field_type">recref</value>
        <value name="field_dim">0</value>
        <value name="nillable">true</value>
        <value name="form_qualified">false</value>
        <value name="is_global">false</value>
        <value name="modifiable">true</value>
        <value name="rec_ref">MdrDbtOnlineOnboarding.documents.process:ResumeProcess</value>
      </record>
      <record javaclass="com.wm.util.Values">
        <value name="node_type">unknown</value>
        <value name="node_subtype">unknown</value>
        <value name="is_public">false</value>
        <value name="field_name">stageNo</value>
        <value name="field_type">string</value>
        <value name="field_dim">0</value>
        <value name="nillable">true</value>
        <value name="form_qualified">false</value>
        <value name="is_global">false</value>
      </record>
      <record javaclass="com.wm.util.Values">
        <value name="node_type">record</value>
        <value name="node_subtype">unknown</value>
        <value name="node_comment"></value>
        <record name="node_hints" javaclass="com.wm.util.Values">
          <value name="field_largerEditor">false</value>
          <value name="field_password">false</value>
        </record>
        <value name="is_public">false</value>
        <value name="field_name">instances</value>
        <value name="field_type">record</value>
        <value name="field_dim">0</value>
        <value name="wrapper_type">IData</value>
        <value name="nillable">true</value>
        <value name="form_qualified">false</value>
        <value name="is_global">false</value>
        <array name="rec_fields" type="record" depth="1">
        </array>
        <value name="rec_closed">true</value>
        <value name="modifiable">true</value>
      </record>
    </array>
    <value name="modifiable">true</value>
  </record>
</Values>
</MAPTARGET>
  <MAPSOURCE>

<Values version="2.0">
  <record name="xml" javaclass="com.wm.util.Values">
    <value name="node_type">record</value>
    <value name="node_subtype">unknown</value>
    <value name="is_public">false</value>
    <value name="field_type">record</value>
    <value name="field_dim">0</value>
    <value name="nillable">true</value>
    <value name="form_qualified">false</value>
    <value name="is_global">false</value>
    <array name="rec_fields" type="record" depth="1">
    </array>
    <value name="modifiable">true</value>
  </record>
</Values>
</MAPSOURCE>

  <!-- nodes -->

<MAPSET NAME="Setter" OVERWRITE="true" VARIABLES="false" GLOBALVARIABLES="false" FIELD="/processResume;4;0;MdrDbtOnlineOnboarding.documents.process:ResumeProcess/stage;1;0">
  <DATA ENCODING="XMLValues" I18N="true">

<Values version="2.0">
  <value name="xml">Create CIF Account</value>
  <record name="type" javaclass="com.wm.util.Values">
    <value name="node_type">record</value>
    <value name="node_subtype">unknown</value>
    <value name="node_comment"></value>
    <record name="node_hints" javaclass="com.wm.util.Values">
      <value name="field_usereditable">true</value>
      <value name="field_largerEditor">false</value>
      <value name="field_password">false</value>
    </record>
    <value name="is_public">false</value>
    <value name="field_name">stage</value>
    <value name="field_type">string</value>
    <value name="field_dim">0</value>
    <value name="field_opt">true</value>
    <array name="field_options" type="value" depth="1">
    </array>
    <value name="nillable">true</value>
    <value name="form_qualified">false</value>
    <value name="is_global">false</value>
  </record>
</Values>
</DATA>
</MAPSET>

<MAPSET NAME="Setter" OVERWRITE="true" VARIABLES="false" GLOBALVARIABLES="false" FIELD="/processResume;4;0;MdrDbtOnlineOnboarding.documents.process:ResumeProcess/status;1;0">
  <DATA ENCODING="XMLValues" I18N="true">

<Values version="2.0">
  <value name="xml">Please try again after sometime.</value>
  <record name="type" javaclass="com.wm.util.Values">
    <value name="node_type">record</value>
    <value name="node_subtype">unknown</value>
    <value name="node_comment"></value>
    <record name="node_hints" javaclass="com.wm.util.Values">
      <value name="field_usereditable">true</value>
      <value name="field_largerEditor">false</value>
      <value name="field_password">false</value>
    </record>
    <value name="is_public">false</value>
    <value name="field_name">status</value>
    <value name="field_type">string</value>
    <value name="field_dim">0</value>
    <value name="field_opt">true</value>
    <array name="field_options" type="value" depth="1">
    </array>
    <value name="nillable">true</value>
    <value name="form_qualified">false</value>
    <value name="is_global">false</value>
  </record>
</Values>
</DATA>
</MAPSET>

<MAPSET NAME="Setter" OVERWRITE="true" VARIABLES="true" GLOBALVARIABLES="false" FIELD="/processResume;4;0;MdrDbtOnlineOnboarding.documents.process:ResumeProcess/referenceKey;1;0">
  <DATA ENCODING="XMLValues" I18N="true">

<Values version="2.0">
  <value name="xml">%instances/INSTANCEID%</value>
  <record name="type" javaclass="com.wm.util.Values">
    <value name="node_type">record</value>
    <value name="node_subtype">unknown</value>
    <value name="node_comment"></value>
    <record name="node_hints" javaclass="com.wm.util.Values">
      <value name="field_usereditable">true</value>
      <value name="field_largerEditor">false</value>
      <value name="field_password">false</value>
    </record>
    <value name="is_public">false</value>
    <value name="field_name">referenceKey</value>
    <value name="field_type">string</value>
    <value name="field_dim">0</value>
    <value name="field_opt">true</value>
    <array name="field_options" type="value" depth="1">
    </array>
    <value name="nillable">true</value>
    <value name="form_qualified">false</value>
    <value name="is_global">false</value>
  </record>
</Values>
</DATA>
</MAPSET>
</MAP>
</SEQUENCE>
</BRANCH>
</SEQUENCE>

<MAP TIMEOUT="" MODE="STANDALONE">
  <COMMENT>Drop Variables</COMMENT>
  <MAPTARGET>

<Values version="2.0">
  <record name="xml" javaclass="com.wm.util.Values">
    <value name="node_type">record</value>
    <value name="node_subtype">unknown</value>
    <value name="is_public">false</value>
    <value name="field_type">record</value>
    <value name="field_dim">0</value>
    <value name="nillable">true</value>
    <value name="form_qualified">false</value>
    <value name="is_global">false</value>
    <array name="rec_fields" type="record" depth="1">
    </array>
    <value name="modifiable">true</value>
  </record>
</Values>
</MAPTARGET>
  <MAPSOURCE>

<Values version="2.0">
  <record name="xml" javaclass="com.wm.util.Values">
    <value name="node_type">record</value>
    <value name="node_subtype">unknown</value>
    <value name="is_public">false</value>
    <value name="field_type">record</value>
    <value name="field_dim">0</value>
    <value name="nillable">true</value>
    <value name="form_qualified">false</value>
    <value name="is_global">false</value>
    <array name="rec_fields" type="record" depth="1">
      <record javaclass="com.wm.util.Values">
        <value name="node_type">unknown</value>
        <value name="node_subtype">unknown</value>
        <value name="is_public">false</value>
        <value name="field_name">instanceID</value>
        <value name="field_type">string</value>
        <value name="field_dim">0</value>
        <value name="nillable">true</value>
        <value name="form_qualified">false</value>
        <value name="is_global">false</value>
      </record>
      <record javaclass="com.wm.util.Values">
        <value name="node_type">record</value>
        <value name="node_subtype">unknown</value>
        <value name="is_public">false</value>
        <value name="field_name">processResume</value>
        <value name="field_type">recref</value>
        <value name="field_dim">0</value>
        <value name="nillable">true</value>
        <value name="form_qualified">false</value>
        <value name="is_global">false</value>
        <value name="modifiable">true</value>
        <value name="rec_ref">MdrDbtOnlineOnboarding.documents.process:ResumeProcess</value>
      </record>
      <record javaclass="com.wm.util.Values">
        <value name="node_type">unknown</value>
        <value name="node_subtype">unknown</value>
        <value name="is_public">false</value>
        <value name="field_name">stageNo</value>
        <value name="field_type">string</value>
        <value name="field_dim">0</value>
        <value name="nillable">true</value>
        <value name="form_qualified">false</value>
        <value name="is_global">false</value>
      </record>
      <record javaclass="com.wm.util.Values">
        <value name="node_type">record</value>
        <value name="node_subtype">unknown</value>
        <value name="node_comment"></value>
        <record name="node_hints" javaclass="com.wm.util.Values">
          <value name="field_largerEditor">false</value>
          <value name="field_password">false</value>
        </record>
        <value name="is_public">false</value>
        <value name="field_name">instances</value>
        <value name="field_type">record</value>
        <value name="field_dim">0</value>
        <value name="wrapper_type">IData</value>
        <value name="nillable">true</value>
        <value name="form_qualified">false</value>
        <value name="is_global">false</value>
        <array name="rec_fields" type="record" depth="1">
        </array>
        <value name="rec_closed">true</value>
        <value name="modifiable">true</value>
      </record>
    </array>
    <value name="modifiable">true</value>
  </record>
</Values>
</MAPSOURCE>

  <!-- nodes -->

<MAPDELETE FIELD="/instanceID;1;0">
</MAPDELETE>

<MAPDELETE FIELD="/instances;2;0">
</MAPDELETE>

<MAPDELETE FIELD="/stageNo;1;0">
</MAPDELETE>
</MAP>
</FLOW>
